TkinterMaster/__init__.py
TkinterMaster-1.0.0.dist-info/METADATA
TkinterMaster-1.0.0.dist-info/WHEEL
TkinterMaster-1.0.0.dist-info/top_level.txt
TkinterMaster-1.0.0.dist-info/RECORD
