Metadata-Version: 2.1
Name: TkinterMaster
Version: 1.0.0
Summary: Tkinter functionality
Author: Ronchetti Ezequiel Nicolás
Author-email: RonchettiEzequielNicolas@hotmail.com
Classifier: Programming Language :: Python :: 3
Classifier: License :: OSI Approved :: MIT License
Classifier: Operating System :: OS Independent
Requires-Python: >=3.6
